TheSchemeProgrammingLanguage4e/README.md
TheSchemeProgrammingLanguage4e/__init__.py
TheSchemeProgrammingLanguage4e/__main__.py
TheSchemeProgrammingLanguage4e/file.epub
TheSchemeProgrammingLanguage4e/index.html
TheSchemeProgrammingLanguage4e/css/__init__.py
TheSchemeProgrammingLanguage4e/css/annotations.css
TheSchemeProgrammingLanguage4e/css/main.css
TheSchemeProgrammingLanguage4e/css/normalize.css
TheSchemeProgrammingLanguage4e/css/popup.css
TheSchemeProgrammingLanguage4e/font/__init__.py
TheSchemeProgrammingLanguage4e/font/fontello.eot
TheSchemeProgrammingLanguage4e/font/fontello.svg
TheSchemeProgrammingLanguage4e/font/fontello.ttf
TheSchemeProgrammingLanguage4e/font/fontello.woff
TheSchemeProgrammingLanguage4e/img/__init__.py
TheSchemeProgrammingLanguage4e/img/annotator-glyph-sprite.png
TheSchemeProgrammingLanguage4e/img/annotator-icon-sprite.png
TheSchemeProgrammingLanguage4e/img/apple-touch-icon.png
TheSchemeProgrammingLanguage4e/img/cancelfullscreen.png
TheSchemeProgrammingLanguage4e/img/close.png
TheSchemeProgrammingLanguage4e/img/fullscreen.png
TheSchemeProgrammingLanguage4e/img/loader.gif
TheSchemeProgrammingLanguage4e/img/menu-icon.png
TheSchemeProgrammingLanguage4e/img/save.png
TheSchemeProgrammingLanguage4e/img/saved.png
TheSchemeProgrammingLanguage4e/img/settings-s.png
TheSchemeProgrammingLanguage4e/img/settings.png
TheSchemeProgrammingLanguage4e/img/star.png
TheSchemeProgrammingLanguage4e/js/__init__.py
TheSchemeProgrammingLanguage4e/js/epub.js
TheSchemeProgrammingLanguage4e/js/epub.min.js
TheSchemeProgrammingLanguage4e/js/epub.min.map
TheSchemeProgrammingLanguage4e/js/hooks.min.js
TheSchemeProgrammingLanguage4e/js/hooks.min.map
TheSchemeProgrammingLanguage4e/js/reader.js
TheSchemeProgrammingLanguage4e/js/reader.js.map
TheSchemeProgrammingLanguage4e/js/reader.min.js
TheSchemeProgrammingLanguage4e/js/reader.min.map
TheSchemeProgrammingLanguage4e/js/hooks/__init__.py
TheSchemeProgrammingLanguage4e/js/hooks/extensions/__init__.py
the_scheme_programming_language_4e-2024.3.2.0.dist-info/METADATA
the_scheme_programming_language_4e-2024.3.2.0.dist-info/WHEEL
the_scheme_programming_language_4e-2024.3.2.0.dist-info/entry_points.txt
the_scheme_programming_language_4e-2024.3.2.0.dist-info/top_level.txt
the_scheme_programming_language_4e-2024.3.2.0.dist-info/RECORD
